data2es/__init__.py
data2es/__main__.py
data2es/esHelper.py
data2es/main.py
data2es/maind.py
data2es/myDaemon.py
data2es/mysqlProvider.py
data2es/providerBase.py
data2es/scheduler.py
data2es/webhook.py
data2es-0.0.14.dist-info/LICENSE
data2es-0.0.14.dist-info/METADATA
data2es-0.0.14.dist-info/WHEEL
data2es-0.0.14.dist-info/entry_points.txt
data2es-0.0.14.dist-info/top_level.txt
data2es-0.0.14.dist-info/RECORD
