Metadata-Version: 2.1
Name: data2es
Version: 0.0.14
Summary: A tool to import data from mysql into elasticsearch
Home-page: https://gitee.com/sidaxin/data2es
Author: stosc lee
Author-email: stosc@sidaxin.com
License: MIT Licence
Keywords: data2esb,data2esd,mysql,elasticsearch,import,data
Platform: any
Classifier: Programming Language :: Python :: 3
Requires-Python: >=3.6
Requires-Dist: argparse
Requires-Dist: croniter
Requires-Dist: elasticsearch
Requires-Dist: psutil
Requires-Dist: pyhocon
Requires-Dist: pymysql
Requires-Dist: tornado
